ndevio/__init__.py
ndevio/_bioio_extensions.py
ndevio/_bioio_plugin_utils.py
ndevio/_colormap_utils.py
ndevio/_napari_reader.py
ndevio/_plugin_installer.py
ndevio/_plugin_manager.py
ndevio/helpers.py
ndevio/napari.yaml
ndevio/ndev_settings.yaml
ndevio/nimage.py
ndevio/sampledata/__init__.py
ndevio/sampledata/_sample_data.py
ndevio/sampledata/data/ndev-logo.png
ndevio/sampledata/data/neuron-4Ch_labels.tiff
ndevio/sampledata/data/neuron-4Ch_labels_processed.tiff
ndevio/widgets/__init__.py
ndevio/widgets/_plugin_install_widget.py
ndevio/widgets/_scene_widget.py
ndevio/widgets/_utilities_container.py
ndevio-0.7.0.dist-info/METADATA
ndevio-0.7.0.dist-info/WHEEL
ndevio-0.7.0.dist-info/entry_points.txt
ndevio-0.7.0.dist-info/licenses/LICENSE
ndevio-0.7.0.dist-info/RECORD
