Metadata-Version: 2.4
Name: ndevio
Version: 0.7.0
Summary: Read, write, and manage images in napari
Project-URL: Bug Tracker, https://github.com/ndev-kit/ndevio/issues
Project-URL: Documentation, https://github.com/ndev-kit/ndevio#README.md
Project-URL: Source Code, https://github.com/ndev-kit/ndevio
Project-URL: User Support, https://github.com/ndev-kit/ndevio/issues
Author: Tim Monko
Author-email: timmonko@gmail.com
License-Expression: BSD-3-Clause
License-File: LICENSE
Classifier: Development Status :: 2 - Pre-Alpha
Classifier: Framework :: napari
Classifier: Intended Audience :: Developers
Classifier: Operating System :: OS Independent
Classifier: Programming Language :: Python
Classifier: Programming Language :: Python :: 3
Classifier: Programming Language :: Python :: 3 :: Only
Classifier: Programming Language :: Python :: 3.11
Classifier: Programming Language :: Python :: 3.12
Classifier: Programming Language :: Python :: 3.13
Classifier: Topic :: Scientific/Engineering :: Image Processing
Requires-Python: >=3.11
Requires-Dist: bioio-base
Requires-Dist: bioio-imageio
Requires-Dist: bioio-ome-tiff>=1.2.0
Requires-Dist: bioio-ome-zarr>=3
Requires-Dist: bioio-tifffile
Requires-Dist: bioio>=3.2.0
Requires-Dist: magic-class
Requires-Dist: magicgui
Requires-Dist: napari
Requires-Dist: napari-plugin-manager>=0.1.7
Requires-Dist: natsort
Requires-Dist: nbatch>=0.0.4
Requires-Dist: ndev-settings>=0.4.0
Requires-Dist: pooch
Requires-Dist: xarray
Requires-Dist: zarr>=3.1.3
Provides-Extra: all
Requires-Dist: napari[all]; extra == 'all'
